a2t/__init__.py
a2t/base.py
a2t/evaluation.py
a2t/utils.py
a2t/data/__init__.py
a2t/data/ace.py
a2t/data/babeldomains.py
a2t/data/base.py
a2t/data/tacred.py
a2t/data/wikievents.py
a2t/legacy/__init__.py
a2t/legacy/relation_classification/__init__.py
a2t/legacy/relation_classification/mnli.py
a2t/legacy/relation_classification/run_evaluation.py
a2t/legacy/relation_classification/run_glue.py
a2t/legacy/relation_classification/tacred.py
a2t/legacy/relation_classification/utils.py
a2t/legacy/topic_classification/__init__.py
a2t/legacy/topic_classification/annotate_wordnet.py
a2t/legacy/topic_classification/babeldomains.py
a2t/legacy/topic_classification/base.py
a2t/legacy/topic_classification/finetune_classifier.py
a2t/legacy/topic_classification/mlm.py
a2t/legacy/topic_classification/mnli.py
a2t/legacy/topic_classification/nsp.py
a2t/legacy/topic_classification/run_evaluation.py
a2t/legacy/topic_classification/wndomains.py
a2t/tasks/__init__.py
a2t/tasks/base.py
a2t/tasks/span_classification.py
a2t/tasks/text_classification.py
a2t/tasks/tuple_classification.py
a2t/tests/__init__.py
a2t/tests/test_data.py
a2t/tests/test_inference.py
a2t/tests/test_tasks.py
a2t-0.4.0.dist-info/LICENSE
a2t-0.4.0.dist-info/METADATA
a2t-0.4.0.dist-info/WHEEL
a2t-0.4.0.dist-info/top_level.txt
a2t-0.4.0.dist-info/RECORD
