Metadata-Version: 2.1
Name: a2t
Version: 0.4.0
Summary: Ask2Transformers is a library for zero-shot classification based on Transformers.
Home-page: https://github.com/osainz59/Ask2Transformers
Author: Oscar Sainz
Author-email: oscar.sainz@ehu.eus
License: UNKNOWN
Platform: UNKNOWN
Classifier: Programming Language :: Python :: 3
Classifier: License :: OSI Approved :: Apache Software License
Classifier: Operating System :: OS Independent
Requires-Python: >=3.6
License-File: LICENSE
Requires-Dist: transformers
Requires-Dist: tqdm
Requires-Dist: torch
Requires-Dist: numpy
Requires-Dist: scikit-learn
